flame_analyzer/__init__.py
flame_analyzer/context_managers.py
flame_analyzer/flamegraph.pl
flame_analyzer/hooks.py
flame_analyzer/sample.py
flame_analyzer/utils.py
flame_analyzer-0.1.5.dist-info/LICENSE
flame_analyzer-0.1.5.dist-info/METADATA
flame_analyzer-0.1.5.dist-info/WHEEL
flame_analyzer-0.1.5.dist-info/top_level.txt
flame_analyzer-0.1.5.dist-info/RECORD
