Metadata-Version: 2.1
Name: flame-analyzer
Version: 0.1.5
Summary: A small Django and IPython compatible application for benchmarking database and IO heavy work.
Home-page: https://github.com/publons/flame-analyzer
Author: Matthew Betts, Aidan Houlihan
Author-email: aidan@publons.com
License: MIT License
Platform: UNKNOWN
Classifier: Environment :: Web Environment
Classifier: Framework :: Django
Classifier: Intended Audience :: Developers
Classifier: License :: OSI Approved :: BSD License
Classifier: Operating System :: OS Independent
Classifier: Programming Language :: Python
Classifier: Programming Language :: Python :: 3.0
Classifier: Programming Language :: Python :: 3.6
Classifier: Topic :: Internet :: WWW/HTTP
Classifier: Topic :: Internet :: WWW/HTTP :: Dynamic Content
